terrarium/__init__.py
terrarium/terrarium.py
terrarium-1.2.0.dist-info/LICENSE
terrarium-1.2.0.dist-info/METADATA
terrarium-1.2.0.dist-info/WHEEL
terrarium-1.2.0.dist-info/entry_points.txt
terrarium-1.2.0.dist-info/top_level.txt
terrarium-1.2.0.dist-info/zip-safe
terrarium-1.2.0.dist-info/RECORD
