Metadata-Version: 2.1
Name: terrarium
Version: 1.2.0
Summary: Package and ship relocatable Python virtual environments
Home-page: https://terrarium.readthedocs.io/
Author: Kyle Gibson
Author-email: kyle.gibson@frozenonline.com
License: BSD 3-Clause
Project-URL: Source, https://github.com/PolicyStat/terrarium
Project-URL: Tracker, https://github.com/PolicyStat/terrarium/issues
Platform: UNKNOWN
Classifier: Development Status :: 4 - Beta
Classifier: Environment :: Console
Classifier: Intended Audience :: Developers
Classifier: License :: OSI Approved :: BSD License
Classifier: Operating System :: POSIX
Classifier: Topic :: Software Development :: Testing
Classifier: Topic :: Software Development :: Libraries
Classifier: Topic :: Utilities
Classifier: Programming Language :: Python :: 2
Classifier: Programming Language :: Python :: 2.7
Requires-Python: ~=2.7.0
Requires-Dist: virtualenv
